{
    "weaningPeriodData": [
        {
            "link": "/cat-food",
            "imageSrc": "/image/care-for-cat-new/(1.0 cat) baby kitten kibble.png",
            "altText": "baby kitten kibble",
            "texts": [
                "baby kitten kibble"
            ]
        },
        {
            "link": "/cat-food",
            "imageSrc": "/image/care-for-cat-new/(1.1 cat) KitchenFlavor Grain Free Complete Food for Mother & baby.png",
            "altText": "KitchenFlavor Grain Free Complete Food for Mother & baby",
            "texts": [
                "KitchenFlavor Grain Free Complete Food for Mother & baby"
            ]
        }
    ],
    "childhoodData": [
        {
            "link": "/cat-food",
            "imageSrc": "/image/care-for-cat-new/(2.0 cat) kitten kibble.png",
            "altText": "kitten kibble",
            "texts": [
                "kitten kibble"
            ]
        },
        {
            "link": "/cat-food",
            "imageSrc": "/image/care-for-cat-new/(2.1 cat) KitchenFlavor Grain Free Complete Food for Kitten.png",
            "altText": "KitchenFlavor Grain Free Complete Food for Kitten",
            "texts": [
                "KitchenFlavor Grain Free Complete Food for Kitten"
            ]
        }
    ],
    "adulthoodData": [
        {
            "link": "/cat-food",
            "imageSrc": "/image/care-for-cat-new/(3.0 cat)adult kibble.png",
            "altText": "adult kibbl",
            "texts": [
                "adult kibbl"
            ]
        },
        {
            "link": "/cat-food",
            "imageSrc": "/image/care-for-cat-new/(3.1 cat)KitchenFlavor Grain Free Complete Food for Adult Cat).png",
            "altText": "KitchenFlavor Grain Free Complete Food for Adult Cat",
            "texts": [
                "KitchenFlavor Grain Free Complete Food for Adult Cat"
            ]
        },
        {
            "link": "/cat-food",
            "imageSrc": "/image/care-for-cat-new/(3.2 cat) KitchenFlavor Special Care Urinary Care Complete Food for Adult Cat.png",
            "altText": "KitchenFlavor Special Care Urinary Care Complete Food for Adult Cat",
            "texts": [
                "KitchenFlavor Special Care Urinary Care Complete Food for Adult Cat"
            ]
        }
    ],
    "oldAgeData": [
        {
            "link": "/cat-food",
            "imageSrc": "/image/care-for-cat-new/(4.0 cat) kibble.png",
            "altText": "kibble",
            "texts": [
                "kibble"
            ]
        },
        {
            "link": "/cat-food",
            "imageSrc": "/image/care-for-cat-new/(4.1 Cat) KitchenFlavor Pate Delight Salmon Complete Wet Food for Beauty Cat for All Life Stages.png",
            "altText": "KitchenFlavor Pate Delight Salmon Complete Wet Food for Beauty Cat for All Life Stages",
            "texts": [
                "KitchenFlavor Pate Delight Salmon Complete Wet Food for Beauty Cat for All Life Stages"
            ]
        },
        {
            "link": "/cat-food",
            "imageSrc": "/image/care-for-cat-new/(4.2 Cat) KitchenFlavor Grain Free Complete Beauty Cat Food for All Life Stages.png",
            "altText": "KitchenFlavor Grain Free Complete Beauty Cat Food for All Life Stages",
            "texts": [
                "KitchenFlavor Grain Free Complete Beauty Cat Food for All Life Stages"
            ]
        }
    ]
}
